nbmf_mm/__init__.py
nbmf_mm/_base.py
nbmf_mm/_solver.py
nbmf_mm/_utils.py
nbmf_mm/_version.py
nbmf_mm-0.1.4.dist-info/licenses/LICENSE.md
nbmf_mm-0.1.4.dist-info/METADATA
nbmf_mm-0.1.4.dist-info/WHEEL
nbmf_mm-0.1.4.dist-info/top_level.txt
nbmf_mm-0.1.4.dist-info/RECORD
