Metadata-Version: 2.4
Name: nbmf-mm
Version: 0.1.4
Summary: Bernoulli (binary) mean-parameterized NMF (NBMF) w/ Majorization–Minimization (MM)
Author-email: "Siddharth M. Chauhan" <github.chauhan.siddharth@gmail.com>
Project-URL: Homepage, https://github.com/siddC/nbmf_mm
Project-URL: Issues, https://github.com/siddC/nbmf_mm/issues
Project-URL: Repository, https://github.com/siddC/nbmf_mm
Keywords: NMF,Bernoulli,matrix factorization,topic modeling,ICA,Dirichlet,Beta
Classifier: Programming Language :: Python :: 3 :: Only
Classifier: Programming Language :: Python :: 3.9
Classifier: Programming Language :: Python :: 3.10
Classifier: Programming Language :: Python :: 3.11
Classifier: Programming Language :: Python :: 3.12
Classifier: License :: OSI Approved :: MIT License
Classifier: Intended Audience :: Science/Research
Classifier: Topic :: Scientific/Engineering :: Information Analysis
Classifier: Topic :: Scientific/Engineering :: Bio-Informatics
Classifier: Topic :: Scientific/Engineering :: Artificial Intelligence
Classifier: Topic :: Software Development :: Libraries :: Python Modules
Requires-Python: <3.13,>=3.9
License-File: LICENSE.md
Requires-Dist: numpy>=1.22
Requires-Dist: scipy>=1.9
Requires-Dist: scikit-learn>=1.3
Requires-Dist: matplotlib>=3.5
Provides-Extra: tests
Requires-Dist: pytest>=7.2; extra == "tests"
Requires-Dist: pytest-cov>=4.0; extra == "tests"
Provides-Extra: docs
Requires-Dist: sphinx>=7.0; extra == "docs"
Requires-Dist: furo>=2023.9.10; extra == "docs"
Requires-Dist: myst-parser>=2.0; extra == "docs"
Provides-Extra: dev
Requires-Dist: black>=24.0; extra == "dev"
Requires-Dist: ruff>=0.4; extra == "dev"
Requires-Dist: build>=1.2; extra == "dev"
Requires-Dist: twine>=5.0; extra == "dev"
Provides-Extra: accel
Requires-Dist: numexpr>=2.8; extra == "accel"
Requires-Dist: numba>=0.60; python_version >= "3.10" and extra == "accel"
Provides-Extra: all
Requires-Dist: scikit-learn>=1.3; extra == "all"
Requires-Dist: numexpr>=2.8; extra == "all"
Requires-Dist: numba>=0.60; python_version >= "3.10" and extra == "all"
Provides-Extra: r
Requires-Dist: rpy2>=3.5; extra == "r"
Provides-Extra: all-r
Requires-Dist: scikit-learn>=1.3; extra == "all-r"
Requires-Dist: numexpr>=2.8; extra == "all-r"
Requires-Dist: numba>=0.60; python_version >= "3.10" and extra == "all-r"
Requires-Dist: rpy2>=3.5; extra == "all-r"
Dynamic: license-file
